{
  "actualizado": "15/07/2026 20:13 UTC",
  "periodo": "Últimos 30 días · Google Trends MX",
  "total": 10,
  "trends": [
    {
      "titulo": "rice",
      "descripcion": "England to make late call on Rice for World Cup semi-final",
      "trafico": "2000+",
      "fecha": "15/07/2026 20:00",
      "fecha_dt": "2026-07-15T20:00:00+00:00",
      "imagen": "https://encrypted-tbn2.gstatic.com/images?q=tbn:ANd9GcTmuZ9z-YQd9cvCZC6VT4-F2XyLD6phOVNaHFb2KJW5SSAuYsrYplVvGlAbeU0",
      "link": "https://trends.google.com/trending?geo=MX&q=rice",
      "status": ""
    },
    {
      "titulo": "lisandro martínez",
      "descripcion": "El original ritual de Cuti Romero y Licha Martínez que podría repetirse en el partido de Argentina contra Inglaterra",
      "trafico": "2000+",
      "fecha": "15/07/2026 19:40",
      "fecha_dt": "2026-07-15T19:40:00+00:00",
      "imagen": "https://encrypted-tbn2.gstatic.com/images?q=tbn:ANd9GcTu67dxf8cidvMN7QR4Uf6zm-f1RcfFcSMCVZxvFry9Torm54dNcnyUK_KbrtE",
      "link": "https://trends.google.com/trending?geo=MX&q=lisandro+martínez",
      "status": ""
    },
    {
      "titulo": "elliot anderson",
      "descripcion": "Why Elliot Anderson's hard tackle on Lionel Messi resulted in yellow card vs. Argentina",
      "trafico": "1000+",
      "fecha": "15/07/2026 19:40",
      "fecha_dt": "2026-07-15T19:40:00+00:00",
      "imagen": "https://encrypted-tbn2.gstatic.com/images?q=tbn:ANd9GcRvp7qjjBj3UPyF7VWirWFBAYHO4PGn7TyJKob13PQJsauoScU2z1i_MPM8QMk",
      "link": "https://trends.google.com/trending?geo=MX&q=elliot+anderson",
      "status": ""
    },
    {
      "titulo": "gordon inglaterra",
      "descripcion": "La mansión de 3 millones de euros que Anthony Gordon deja atrás para mudarse a Barcelona: una sauna con jacuzzi y un jardín protagonista",
      "trafico": "1000+",
      "fecha": "15/07/2026 19:40",
      "fecha_dt": "2026-07-15T19:40:00+00:00",
      "imagen": "https://encrypted-tbn3.gstatic.com/images?q=tbn:ANd9GcSVXrzpcklBHk9sWDvv4OwvwfogrLA5LL7rYi0RLCY7CsdtMkiLyCdaR9YR3Ak",
      "link": "https://trends.google.com/trending?geo=MX&q=gordon+inglaterra",
      "status": ""
    },
    {
      "titulo": "john stones",
      "descripcion": "Leeds news: Fan views on free agents and targets to avoid",
      "trafico": "500+",
      "fecha": "15/07/2026 19:50",
      "fecha_dt": "2026-07-15T19:50:00+00:00",
      "imagen": "https://encrypted-tbn0.gstatic.com/images?q=tbn:ANd9GcQjhHg09p3gxULWFdqBpguPs6VBKMBEGA7yoywqB5ns1SGyoVrtBTaYSCpBjaU",
      "link": "https://trends.google.com/trending?geo=MX&q=john+stones",
      "status": ""
    },
    {
      "titulo": "ucrania",
      "descripcion": "Von der Leyen anuncia acuerdo sobre drones de UE y Ucrania",
      "trafico": "200+",
      "fecha": "15/07/2026 20:00",
      "fecha_dt": "2026-07-15T20:00:00+00:00",
      "imagen": "https://encrypted-tbn2.gstatic.com/images?q=tbn:ANd9GcQElwVV5UsHHX1jYI6-gmVq0Vrt5jvPWdLmaIj_2e-xNGp-7PrFdDleHAycc9I",
      "link": "https://trends.google.com/trending?geo=MX&q=ucrania",
      "status": ""
    },
    {
      "titulo": "rice inglaterra",
      "descripcion": "La historia de amor de Declan Rice y la encendida defensa a su novia ante el acoso por su aspecto físico",
      "trafico": "200+",
      "fecha": "15/07/2026 20:00",
      "fecha_dt": "2026-07-15T20:00:00+00:00",
      "imagen": "https://encrypted-tbn2.gstatic.com/images?q=tbn:ANd9GcTiEeCiumFVjIu7Vt_mVTJhnq_iwynQfjoLJDUgsZgyJW1UoBRsg21EokqfVCg",
      "link": "https://trends.google.com/trending?geo=MX&q=rice+inglaterra",
      "status": ""
    },
    {
      "titulo": "nahuel guzmán",
      "descripcion": "Nahuel Guzmán es suspendido SIETE PARTIDOS por Concacaf",
      "trafico": "200+",
      "fecha": "15/07/2026 20:00",
      "fecha_dt": "2026-07-15T20:00:00+00:00",
      "imagen": "https://encrypted-tbn1.gstatic.com/images?q=tbn:ANd9GcS_qUJyx5AACphUMcbiXXfZwKIZvb9fPLxemnS8JaYaKZo8JuSaQ18SVokrOJo",
      "link": "https://trends.google.com/trending?geo=MX&q=nahuel+guzmán",
      "status": ""
    },
    {
      "titulo": "reino unido",
      "descripcion": "Sánchez tras la desaparición de la Verja de Gibraltar: “Cae el último muro de la Europa continental”",
      "trafico": "200+",
      "fecha": "15/07/2026 20:00",
      "fecha_dt": "2026-07-15T20:00:00+00:00",
      "imagen": "https://encrypted-tbn3.gstatic.com/images?q=tbn:ANd9GcSBw5qPDlQCw-dsP6nPYAm4nCtJEw-bvq10j8ZovrkLAs-bbne8xmi9_9fFISE",
      "link": "https://trends.google.com/trending?geo=MX&q=reino+unido",
      "status": ""
    },
    {
      "titulo": "cuanto mide jude bellingham",
      "descripcion": "Los Tres Leones se preparan para enfrentar a Argentina, Kane y Bellingham calientan motores",
      "trafico": "100+",
      "fecha": "15/07/2026 20:00",
      "fecha_dt": "2026-07-15T20:00:00+00:00",
      "imagen": "https://encrypted-tbn3.gstatic.com/images?q=tbn:ANd9GcRmQJCzrGjKDVXMSO051W0dnsPJaHDKyMyRISPvPpgV3ZZD1kphLP8a4vok33Q",
      "link": "https://trends.google.com/trending?geo=MX&q=cuanto+mide+jude+bellingham",
      "status": ""
    }
  ]
}