{
  "actualizado": "25/06/2026 23:55 UTC",
  "periodo": "Últimos 30 días · Google Trends MX",
  "total": 10,
  "trends": [
    {
      "titulo": "túnez - países bajos",
      "descripcion": "¡Autogol tempranero! Países Bajos toma ventaja ante Túnez",
      "trafico": "100000+",
      "fecha": "25/06/2026 22:10",
      "fecha_dt": "2026-06-25T22:10:00+00:00",
      "imagen": "https://encrypted-tbn3.gstatic.com/images?q=tbn:ANd9GcTJHcYIIifKmsm9UK3nstu9g6qDIRBMK7LDlS2Te8Z9RaveWot3Hol_lwUG67A",
      "link": "https://trends.google.com/trending?geo=MX&q=túnez+-+países+bajos",
      "status": ""
    },
    {
      "titulo": "japón - suecia",
      "descripcion": "Japón vs. Suecia EN VIVO partido HOY Mundial 2026: minuto a minuto",
      "trafico": "100000+",
      "fecha": "25/06/2026 22:10",
      "fecha_dt": "2026-06-25T22:10:00+00:00",
      "imagen": "https://encrypted-tbn1.gstatic.com/images?q=tbn:ANd9GcSiRBA3Al8kEGdUM8FwxjC-cdtypB-s_CTjUlk6gto03e38TKy29yuZxD7Ckyo",
      "link": "https://trends.google.com/trending?geo=MX&q=japón+-+suecia",
      "status": ""
    },
    {
      "titulo": "japan vs sweden",
      "descripcion": "Japan v Sweden: World Cup 2026 – live",
      "trafico": "5000+",
      "fecha": "25/06/2026 22:10",
      "fecha_dt": "2026-06-25T22:10:00+00:00",
      "imagen": "https://encrypted-tbn3.gstatic.com/images?q=tbn:ANd9GcQZxgQw9YXXanRXJMfZD0raKQvAh4ezkc0DHZtg7mqz___oXf-VPbKUqXqkE1I",
      "link": "https://trends.google.com/trending?geo=MX&q=japan+vs+sweden",
      "status": ""
    },
    {
      "titulo": "tunisia vs netherlands",
      "descripcion": "(2) Tunisia v Netherlands: World Cup 2026 – live",
      "trafico": "2000+",
      "fecha": "25/06/2026 22:10",
      "fecha_dt": "2026-06-25T22:10:00+00:00",
      "imagen": "https://encrypted-tbn0.gstatic.com/images?q=tbn:ANd9GcSaGp79Wwz6kQK7fg2KPzsXNhmvlyVPC4fPCBmecMiJSzW71zGRMfzan2C1XJ8",
      "link": "https://trends.google.com/trending?geo=MX&q=tunisia+vs+netherlands",
      "status": ""
    },
    {
      "titulo": "red sox - yankees",
      "descripcion": "MLB: New York Yankees at Boston Red Sox",
      "trafico": "1000+",
      "fecha": "25/06/2026 23:00",
      "fecha_dt": "2026-06-25T23:00:00+00:00",
      "imagen": "https://encrypted-tbn1.gstatic.com/images?q=tbn:ANd9GcSX2io6R-5OPdlgqsQPZQenDUY5Pn4HdHVJr0bEU4y0EtpE07qcz2F1flKYub8",
      "link": "https://trends.google.com/trending?geo=MX&q=red+sox+-+yankees",
      "status": ""
    },
    {
      "titulo": "paises bajos fc",
      "descripcion": "El Sevilla evita el Sánchez-Pizjuán antes de que arranque la nueva temporada",
      "trafico": "500+",
      "fecha": "25/06/2026 23:20",
      "fecha_dt": "2026-06-25T23:20:00+00:00",
      "imagen": "https://encrypted-tbn1.gstatic.com/images?q=tbn:ANd9GcQtw3eCNSwD6XViUscOVZ2F1suF9U-DK-RMLPC50O6ORvOVyX274UC6m62LHd0",
      "link": "https://trends.google.com/trending?geo=MX&q=paises+bajos+fc",
      "status": ""
    },
    {
      "titulo": "donald trump",
      "descripcion": "IRGC drones targeted ships in Strait of Hormuz after signing of US-Iran deal",
      "trafico": "500+",
      "fecha": "25/06/2026 23:00",
      "fecha_dt": "2026-06-25T23:00:00+00:00",
      "imagen": "https://encrypted-tbn0.gstatic.com/images?q=tbn:ANd9GcSpmYVyeiz9zMH7qBnsYPadWu-l76HvGn_Xzx5QXmXsh7pJB8ufyy4JmBzfbLE",
      "link": "https://trends.google.com/trending?geo=MX&q=donald+trump",
      "status": ""
    },
    {
      "titulo": "bbc sport",
      "descripcion": "Elliot Anderson: Manchester City agree £130m deal with Nottingham Forest for England midfielder",
      "trafico": "500+",
      "fecha": "25/06/2026 23:00",
      "fecha_dt": "2026-06-25T23:00:00+00:00",
      "imagen": "https://encrypted-tbn0.gstatic.com/images?q=tbn:ANd9GcTw_eN_Qc102cZb1giHc6DnTgbBUZz6Yt_UzW7HkjCv6Oihc9pyvqRmPn6QXmY",
      "link": "https://trends.google.com/trending?geo=MX&q=bbc+sport",
      "status": ""
    },
    {
      "titulo": "sindicato",
      "descripcion": "Denuncian desabasto de medicamentos y equipo en hospital del IMSS-Bienestar en Oaxaca",
      "trafico": "500+",
      "fecha": "25/06/2026 22:10",
      "fecha_dt": "2026-06-25T22:10:00+00:00",
      "imagen": "https://encrypted-tbn1.gstatic.com/images?q=tbn:ANd9GcRYzpIxdNKFqGJoJpREJdoZ7nAig3mgmUL0FT3MjlGAFlH9WRcigtzLojuLOZ0",
      "link": "https://trends.google.com/trending?geo=MX&q=sindicato",
      "status": ""
    },
    {
      "titulo": "enrique inzunza cázarez",
      "descripcion": "Reaparece Inzunza en reunión virtual de comisión del Senado",
      "trafico": "200+",
      "fecha": "25/06/2026 23:10",
      "fecha_dt": "2026-06-25T23:10:00+00:00",
      "imagen": "https://encrypted-tbn2.gstatic.com/images?q=tbn:ANd9GcTl5gjpEv5fV-r2lslT-Rvr4rzlTs6g39UlpEQo9N8zBXcymGlCzCaXdfIHyzM",
      "link": "https://trends.google.com/trending?geo=MX&q=enrique+inzunza+cázarez",
      "status": ""
    }
  ]
}