{
  "actualizado": "23/07/2026 10:26 UTC",
  "periodo": "Últimos 30 días · Google Trends MX",
  "total": 10,
  "trends": [
    {
      "titulo": "melate 4242",
      "descripcion": "Resultados Melate, Revancha y Revanchita 4242: números ganadores sorteo del miércoles 22 de Julio 2026",
      "trafico": "1000+",
      "fecha": "23/07/2026 05:00",
      "fecha_dt": "2026-07-23T05:00:00+00:00",
      "imagen": "https://encrypted-tbn0.gstatic.com/images?q=tbn:ANd9GcRSxK_TVZ9FHhzPzQB7ckQdLOwYp32GbKm9VUX5huuh0T27QOaY1-plsRmmirk",
      "link": "https://trends.google.com/trending?geo=MX&q=melate+4242",
      "status": ""
    },
    {
      "titulo": "príncipe george",
      "descripcion": "Prince George enjoys coastal fun in new video as he becomes a teenager",
      "trafico": "500+",
      "fecha": "23/07/2026 06:30",
      "fecha_dt": "2026-07-23T06:30:00+00:00",
      "imagen": "https://encrypted-tbn2.gstatic.com/images?q=tbn:ANd9GcTLqo9aBVRW__3ke0nEmrDnba9RfmT3plHBRtDr-rCAX4bfaMflDIZWilCfXZU",
      "link": "https://trends.google.com/trending?geo=MX&q=príncipe+george",
      "status": ""
    },
    {
      "titulo": "clima culiacan",
      "descripcion": "Clima en Culiacán: Jueves 23 de julio con calor extremo y sensación térmica elevada",
      "trafico": "500+",
      "fecha": "23/07/2026 06:00",
      "fecha_dt": "2026-07-23T06:00:00+00:00",
      "imagen": "https://encrypted-tbn3.gstatic.com/images?q=tbn:ANd9GcSSov7bm8x_P4oh__baTyrRe2-q4wCqGX3ePi3prE2KkgRF2xjdYzoJoxDb7kw",
      "link": "https://trends.google.com/trending?geo=MX&q=clima+culiacan",
      "status": ""
    },
    {
      "titulo": "futbol toluca vs pumas",
      "descripcion": "¿Qué es la Ley del Ex que Toluca sufrió ante Pumas?",
      "trafico": "500+",
      "fecha": "23/07/2026 04:20",
      "fecha_dt": "2026-07-23T04:20:00+00:00",
      "imagen": "https://encrypted-tbn0.gstatic.com/images?q=tbn:ANd9GcRx1O_Bdshzhvg3whu6CFQBw8EFvJZbbN2rByP50MJZdxQRKHHRBVuLdbN1YZE",
      "link": "https://trends.google.com/trending?geo=MX&q=futbol+toluca+vs+pumas",
      "status": ""
    },
    {
      "titulo": "nadia ferreira",
      "descripcion": "Marc Anthony y Nadia Ferreira dan la bienvenida a su segundo hijo",
      "trafico": "200+",
      "fecha": "23/07/2026 05:00",
      "fecha_dt": "2026-07-23T05:00:00+00:00",
      "imagen": "https://encrypted-tbn2.gstatic.com/images?q=tbn:ANd9GcRGrslg7Ly1Lip-CKaQUjkpysDRKxuP35I-OzNPx2eHNrj0iHcXA_uAx2RHq3Q",
      "link": "https://trends.google.com/trending?geo=MX&q=nadia+ferreira",
      "status": ""
    },
    {
      "titulo": "copa mundial de fútbol de 2030",
      "descripcion": "Mundial 2030: Lo que debes saber sobre la edición del centenario",
      "trafico": "200+",
      "fecha": "23/07/2026 05:00",
      "fecha_dt": "2026-07-23T05:00:00+00:00",
      "imagen": "https://encrypted-tbn3.gstatic.com/images?q=tbn:ANd9GcQCbwbjwfCCWHXa4Z718BL01nr16rsUkKIfZQPsFn0JSP_e3roKvdKMWewMeRE",
      "link": "https://trends.google.com/trending?geo=MX&q=copa+mundial+de+fútbol+de+2030",
      "status": ""
    },
    {
      "titulo": "clima morelia",
      "descripcion": "Pronóstico del clima en Morelia, Michoacán hoy 23 de julio de 2026",
      "trafico": "200+",
      "fecha": "23/07/2026 04:50",
      "fecha_dt": "2026-07-23T04:50:00+00:00",
      "imagen": "https://encrypted-tbn1.gstatic.com/images?q=tbn:ANd9GcRMkLCdm7dQuwq8VpD0c5-a1we0x0t_2sM0Sx-6pKo-q0nCvHTiUzhLGkcK9fs",
      "link": "https://trends.google.com/trending?geo=MX&q=clima+morelia",
      "status": ""
    },
    {
      "titulo": "dinero",
      "descripcion": "Once detenidos por blanquear dinero de la droga a través de negocios de ocio y restauración en Sevilla y Cádiz",
      "trafico": "200+",
      "fecha": "23/07/2026 04:20",
      "fecha_dt": "2026-07-23T04:20:00+00:00",
      "imagen": "https://encrypted-tbn1.gstatic.com/images?q=tbn:ANd9GcQzYBhfIdhATwWNVpPTwBS4C_JUonUD04fP_vLLu9m4pW9-vGQGIxadVhYKO8k",
      "link": "https://trends.google.com/trending?geo=MX&q=dinero",
      "status": ""
    },
    {
      "titulo": "dallas vs",
      "descripcion": "WNBA: Dallas Wings at Portland Fire",
      "trafico": "200+",
      "fecha": "23/07/2026 04:20",
      "fecha_dt": "2026-07-23T04:20:00+00:00",
      "imagen": "https://encrypted-tbn2.gstatic.com/images?q=tbn:ANd9GcTlnRzIcpFFcnwscAePtgx_a0ayrTgTTTFiAjDVIr-yQUxPg0Q9HFAvrF7M9sg",
      "link": "https://trends.google.com/trending?geo=MX&q=dallas+vs",
      "status": ""
    },
    {
      "titulo": "bella thorne",
      "descripcion": "Anthony Mackie vs Bella Thorne — Compared",
      "trafico": "100+",
      "fecha": "23/07/2026 08:40",
      "fecha_dt": "2026-07-23T08:40:00+00:00",
      "imagen": "https://encrypted-tbn3.gstatic.com/images?q=tbn:ANd9GcRZTmY2T00IZfYPyIrBj4pTGWBm0m2vxEj15NGPQuhBb9y3o1eOsgox6qfdZ3E",
      "link": "https://trends.google.com/trending?geo=MX&q=bella+thorne",
      "status": ""
    }
  ]
}